dataprep_example/__init__.py
dataprep_example/ingest_retailrocket_dataset.py
dataprep_example/repartition.py
frocket/__init__.py
frocket/apiserver.py
frocket/cli.py
frocket/cli_commands.py
frocket/common/__init__.py
frocket/common/config.py
frocket/common/dataset.py
frocket/common/metrics.py
frocket/common/serializable.py
frocket/common/helpers/__init__.py
frocket/common/helpers/pandas.py
frocket/common/helpers/storage.py
frocket/common/helpers/utils.py
frocket/common/tasks/__init__.py
frocket/common/tasks/async_tracker.py
frocket/common/tasks/base.py
frocket/common/tasks/query.py
frocket/common/tasks/registration.py
frocket/common/validation/__init__.py
frocket/common/validation/consts.py
frocket/common/validation/error.py
frocket/common/validation/path_visitor.py
frocket/common/validation/query_validator.py
frocket/common/validation/relation_parser.py
frocket/common/validation/result.py
frocket/common/validation/visitor_functions.py
frocket/datastore/__init__.py
frocket/datastore/blobstore.py
frocket/datastore/datastore.py
frocket/datastore/redis_store.py
frocket/datastore/registered_datastores.py
frocket/engine/__init__.py
frocket/engine/query_engine.py
frocket/engine/relation_to_pandas.py
frocket/invoker/__init__.py
frocket/invoker/base_invoker.py
frocket/invoker/invoker_api.py
frocket/invoker/metrics_frame.py
frocket/invoker/prom_adapter.py
frocket/invoker/stats_builder.py
frocket/invoker/impl/__init__.py
frocket/invoker/impl/async_invoker.py
frocket/invoker/impl/aws_lambda_invoker.py
frocket/invoker/impl/registered_invokers.py
frocket/invoker/impl/work_queue_invoker.py
frocket/invoker/jobs/__init__.py
frocket/invoker/jobs/job.py
frocket/invoker/jobs/query_job.py
frocket/invoker/jobs/registration_job.py
frocket/resources/query_schema.json
frocket/worker/__init__.py
frocket/worker/impl/__init__.py
frocket/worker/impl/aws_lambda_metrics.py
frocket/worker/impl/aws_lambda_worker.py
frocket/worker/impl/generic_env_metrics.py
frocket/worker/impl/queue_worker.py
funnel_rocket-0.5.3.dist-info/LICENSE
funnel_rocket-0.5.3.dist-info/METADATA
funnel_rocket-0.5.3.dist-info/WHEEL
funnel_rocket-0.5.3.dist-info/top_level.txt
funnel_rocket-0.5.3.dist-info/RECORD
