Metadata-Version: 2.1
Name: funnel-rocket
Version: 0.5.3
Summary: Cloud native distributed funnel queries
Home-page: https://github.com/DynamicYieldProjects/funnel-rocket-oss
Author: Elad Rosenheim, Avshalom Manevich
Author-email: elad@dynamicyield.com
License: UNKNOWN
Platform: UNKNOWN
Classifier: Programming Language :: Python :: 3.8
Classifier: Programming Language :: Python :: 3.9
Classifier: License :: OSI Approved :: Apache Software License
Classifier: Operating System :: OS Independent
Requires-Python: >=3.8
Requires-Dist: pyarrow (>=2.0.0)
Requires-Dist: pandas (>=1.2.0)
Requires-Dist: boto3 (>=1.16.0)
Requires-Dist: redis (>=3.5.0)
Requires-Dist: tabulate (>=0.8.0)
Requires-Dist: prometheus-client (>=0.9.0)
Requires-Dist: flask (>=1.1.0)
Requires-Dist: jsonschema (>=3.2.0)
Requires-Dist: dataclasses-json (>=0.5.2)
Requires-Dist: inflection (>=0.5.0)
Requires-Dist: parsimonious (>=0.8.0)
Requires-Dist: gunicorn (>=20.0.0)
